nimbasms/__init__.py
nimbasms/execptions.py
nimbasms/rest.py
tests/__init__.py
nimbasms-1.0.2.dist-info/LICENSE
nimbasms-1.0.2.dist-info/METADATA
nimbasms-1.0.2.dist-info/WHEEL
nimbasms-1.0.2.dist-info/top_level.txt
nimbasms-1.0.2.dist-info/RECORD
