Metadata-Version: 2.1
Name: nimbasms
Version: 1.0.2
Summary: Python Client Nimba SMS API
Home-page: https://github.com/nimbasms/nimbasms-python
Author: Nimba SMS
Author-email: open-source@nimbasms.com
Classifier: Programming Language :: Python :: 3
Classifier: License :: OSI Approved :: MIT License
Classifier: Operating System :: OS Independent
Requires-Python: >=3.6
License-File: LICENSE
Requires-Dist: requests
